{"Name":"gruvbox Dark","ThemeColorsElements":[{"Name":"ControlBackgroundBrush","ColorString":"#00FFFFFF","ColorLinear":{"StartPoint":"0,0","EndPoint":"0,0","GradientStop1":null,"GradientStop2":null}},{"Name":"TextBrush","ColorString":"#FFFBF1C7","ColorLinear":{"StartPoint":"0,0","EndPoint":"0,0","GradientStop1":null,"GradientStop2":null}},{"Name":"TextBrushDarker","ColorString":"#FFD5C4A1","ColorLinear":{"StartPoint":"0,0","EndPoint":"0,0","GradientStop1":null,"GradientStop2":null}},{"Name":"TextBrushDark","ColorString":"#FFEBDBB2","ColorLinear":{"StartPoint":"0,0","EndPoint":"0,0","GradientStop1":null,"GradientStop2":null}},{"Name":"NormalBrush","ColorString":"#FF7C6F64","ColorLinear":{"StartPoint":"0,0","EndPoint":"0,0","GradientStop1":null,"GradientStop2":null}},{"Name":"NormalBrushDark","ColorString":"#FF665C54","ColorLinear":{"StartPoint":"0,0","EndPoint":"0,0","GradientStop1":null,"GradientStop2":null}},{"Name":"NormalBorderBrush","ColorString":"#FFA89984","ColorLinear":{"StartPoint":"0,0","EndPoint":"0,0","GradientStop1":null,"GradientStop2":null}},{"Name":"HoverBrush","ColorString":"#FF458588","ColorLinear":{"StartPoint":"0,0","EndPoint":"0,0","GradientStop1":null,"GradientStop2":null}},{"Name":"GlyphBrush","ColorString":"#FFA89984","ColorLinear":{"StartPoint":"0,0","EndPoint":"0,0","GradientStop1":null,"GradientStop2":null}},{"Name":"HighlightGlyphBrush","ColorString":"#FF689D6A","ColorLinear":{"StartPoint":"0,0","EndPoint":"0,0","GradientStop1":null,"GradientStop2":null}},{"Name":"PopupBorderBrush","ColorString":"#FFEBDBB2","ColorLinear":{"StartPoint":"0,0","EndPoint":"0,0","GradientStop1":null,"GradientStop2":null}},{"Name":"TooltipBackgroundBrush","ColorString":"#FF282828","ColorLinear":{"StartPoint":"0,0","EndPoint":"0,0","GradientStop1":null,"GradientStop2":null}},{"Name":"ButtonBackgroundBrush","ColorString":"#FF282828","ColorLinear":{"StartPoint":"0,0","EndPoint":"0,0","GradientStop1":null,"GradientStop2":null}},{"Name":"GridItemBackgroundBrush","ColorString":"#FF282828","ColorLinear":{"StartPoint":"0,0","EndPoint":"0,0","GradientStop1":null,"GradientStop2":null}},{"Name":"PanelSeparatorBrush","ColorString":"#FF928374","ColorLinear":{"StartPoint":"0,0","EndPoint":"0,0","GradientStop1":null,"GradientStop2":null}},{"Name":"PopupBackgroundBrush","ColorString":"#FF282828","ColorLinear":{"StartPoint":"0,0","EndPoint":"0,0","GradientStop1":null,"GradientStop2":null}},{"Name":"PositiveRatingBrush","ColorString":"#FF98971A","ColorLinear":{"StartPoint":"0,0","EndPoint":"0,0","GradientStop1":null,"GradientStop2":null}},{"Name":"NegativeRatingBrush","ColorString":"#FFCC241D","ColorLinear":{"StartPoint":"0,0","EndPoint":"0,0","GradientStop1":null,"GradientStop2":null}},{"Name":"MixedRatingBrush","ColorString":"#FFD79921","ColorLinear":{"StartPoint":"0,0","EndPoint":"0,0","GradientStop1":null,"GradientStop2":null}},{"Name":"ExpanderBackgroundBrush","ColorString":"#FF282828","ColorLinear":{"StartPoint":"0,0","EndPoint":"0,0","GradientStop1":null,"GradientStop2":null}},{"Name":"WindowBackgourndBrush","ColorString":"#FF1D2021","ColorLinear":{"StartPoint":"0,0","EndPoint":"0,0","GradientStop1":null,"GradientStop2":null}},{"Name":"WarningBrush","ColorString":"#FFFF7070","ColorLinear":{"StartPoint":"0,0","EndPoint":"0,0","GradientStop1":null,"GradientStop2":null}}]}